{
  "todos": [
    {
      "id": 1,
      "title": "운동짱짱",
      "content": "같이해요",
      "date": "2023-08-16"
    },
    {
      "title": "수영대결하실분",
      "content": "수영 500m",
      "date": "2023-08-10",
      "id": 2
    },
    {
      "id": 3
    },
    {
      "title": "헬스짱",
      "content": "벤치프레스 100개",
      "date": "2023-08-04",
      "id": 4
    },
    {
      "title": "우아아",
      "content": "아하하",
      "date": "2023-09-01",
      "id": 5
    },
    {
      "title": "",
      "content": "1234",
      "date": "2023-08-02",
      "id": 6
    },
    {
      "title": "1234",
      "content": "1234",
      "date": "2023-08-02",
      "id": 7
    },
    {
      "title": "된다 된다리",
      "content": "오챌짱",
      "date": "2023-08-05",
      "id": 8
    },
    {
      "title": "1123",
      "content": "123141",
      "date": "2023-08-12",
      "id": 9
    },
    {
      "title": "ㅂㅈㄷ",
      "content": "324",
      "date": "2023-08-15",
      "id": 10
    }
  ],
  "posts": [
    {
      "id": 1,
      "image": "",
      "crewname": "youngburn",
      "postdate": "2023-08-01",
      "exercisedate": "2023-08-10",
      "location": "서울시 서대문구 서대문로 27로 22",
      "nickname": "KimLee",
      "exercisekind": "축구",
      "totalnumber": "2",
      "title": "용병 구함",
      "content": "youngburn 서대문구에서 용병 구함",
      "date": "2023-08-01"
    },
    {
      "id": 2,
      "image": "",
      "crewname": "youngburn",
      "postdate": "2023-08-01",
      "exercisedate": "2023-08-10",
      "location": "서울시 서대문구 서대문로 27로 22",
      "nickname": "KimLee",
      "exercisekind": "축구",
      "totalnumber": "2",
      "title": "용병 구함",
      "content": "youngburn 서대문구에서 용병 구함",
      "date": "2023-08-01"
    },
    {
      "id": 3,
      "image": "",
      "crewname": "youngburn",
      "postdate": "2023-08-01",
      "exercisedate": "2023-08-10",
      "location": "서울시 서대문구 서대문로 27로 22",
      "nickname": "KimLee",
      "exercisekind": "축구",
      "totalnumber": "2",
      "title": "용병 구함",
      "content": "youngburn 서대문구에서 용병 구함",
      "date": "2023-08-01"
    },
    {
      "id": 4,
      "image": "",
      "crewname": "youngburn",
      "postdate": "2023-08-01",
      "exercisedate": "2023-08-10",
      "location": "서울시 서대문구 서대문로 27로 22",
      "nickname": "KimLee",
      "exercisekind": "축구",
      "totalnumber": "2",
      "title": "용병 구함",
      "content": "youngburn 서대문구에서 용병 구함",
      "date": "2023-08-01"
    },
    {
      "id": 5,
      "image": "",
      "crewname": "youngburn",
      "postdate": "2023-08-01",
      "exercisedate": "2023-08-10",
      "location": "서울시 서대문구 서대문로 27로 22",
      "nickname": "KimLee",
      "exercisekind": "축구",
      "totalnumber": "2",
      "title": "용병 구함",
      "content": "youngburn 서대문구에서 용병 구함",
      "date": "2023-08-01"
    },
    {
      "id": 6,
      "image": "",
      "crewname": "youngburn",
      "postdate": "2023-08-01",
      "exercisedate": "2023-08-10",
      "location": "서울시 서대문구 서대문로 27로 22",
      "nickname": "KimLee",
      "exercisekind": "축구",
      "totalnumber": "2",
      "title": "용병 구함",
      "content": "youngburn 서대문구에서 용병 구함",
      "date": "2023-08-01"
    },
    {
      "id": 7,
      "image": "",
      "crewname": "youngburn",
      "postdate": "2023-08-01",
      "exercisedate": "2023-08-10",
      "location": "서울시 서대문구 서대문로 27로 22",
      "nickname": "KimLee",
      "exercisekind": "축구",
      "totalnumber": "2",
      "title": "용병 구함",
      "content": "youngburn 서대문구에서 용병 구함",
      "date": "2023-08-01"
    },
    {
      "id": 8,
      "image": "",
      "crewname": "youngburn",
      "postdate": "2023-08-01",
      "exercisedate": "2023-08-10",
      "location": "서울시 서대문구 서대문로 27로 22",
      "nickname": "KimLee",
      "exercisekind": "축구",
      "totalnumber": "2",
      "title": "용병 구함",
      "content": "youngburn 서대문구에서 용병 구함",
      "date": "2023-08-01"
    },
    {
      "id": 9,
      "image": "",
      "crewname": "youngburn",
      "postdate": "2023-08-01",
      "exercisedate": "2023-08-10",
      "location": "서울시 서대문구 서대문로 27로 22",
      "nickname": "KimLee",
      "exercisekind": "축구",
      "totalnumber": "2",
      "title": "용병 구함",
      "content": "youngburn 서대문구에서 용병 구함",
      "date": "2023-08-01"
    },
    {
      "id": 10,
      "image": "",
      "crewname": "youngburn",
      "postdate": "2023-08-01",
      "exercisedate": "2023-08-10",
      "location": "서울시 서대문구 서대문로 27로 22",
      "nickname": "KimLee",
      "exercisekind": "축구",
      "totalnumber": "2",
      "title": "용병 구함",
      "content": "youngburn 서대문구에서 용병 구함",
      "date": "2023-08-01"
    },
    {
      "id": 11,
      "image": "",
      "crewname": "youngburn",
      "postdate": "2023-08-01",
      "exercisedate": "2023-08-10",
      "location": "서울시 서대문구 서대문로 27로 22",
      "nickname": "KimLee",
      "exercisekind": "축구",
      "totalnumber": "2",
      "title": "용병 구함",
      "content": "youngburn 서대문구에서 용병 구함",
      "date": "2023-08-01"
    },
    {
      "id": 12,
      "image": "",
      "crewname": "youngburn",
      "postdate": "2023-08-01",
      "exercisedate": "2023-08-10",
      "location": "서울시 서대문구 서대문로 27로 22",
      "nickname": "KimLee",
      "exercisekind": "축구",
      "totalnumber": "2",
      "title": "용병 구함",
      "content": "youngburn 서대문구에서 용병 구함",
      "date": "2023-08-01"
    },
    {
      "id": 13,
      "image": "",
      "crewname": "youngburn",
      "postdate": "2023-08-01",
      "exercisedate": "2023-08-10",
      "location": "서울시 서대문구 서대문로 27로 22",
      "nickname": "KimLee",
      "exercisekind": "축구",
      "totalnumber": "2",
      "title": "용병 구함",
      "content": "youngburn 서대문구에서 용병 구함",
      "date": "2023-08-01"
    },
    {
      "id": 14,
      "image": "",
      "crewname": "youngburn",
      "postdate": "2023-08-01",
      "exercisedate": "2023-08-10",
      "location": "서울시 서대문구 서대문로 27로 22",
      "nickname": "KimLee",
      "exercisekind": "축구",
      "totalnumber": "2",
      "title": "용병 구함",
      "content": "youngburn 서대문구에서 용병 구함",
      "date": "2023-08-01"
    },
    {
      "id": 15,
      "image": "",
      "crewname": "youngburn",
      "postdate": "2023-08-01",
      "exercisedate": "2023-08-10",
      "location": "서울시 서대문구 서대문로 27로 22",
      "nickname": "KimLee",
      "exercisekind": "축구",
      "totalnumber": "2",
      "title": "용병 구함",
      "content": "youngburn 서대문구에서 용병 구함",
      "date": "2023-08-01"
    },
    {
      "id": 16,
      "image": "",
      "crewname": "youngburn",
      "postdate": "2023-08-01",
      "exercisedate": "2023-08-10",
      "location": "서울시 서대문구 서대문로 27로 22",
      "nickname": "KimLee",
      "exercisekind": "축구",
      "totalnumber": "2",
      "title": "용병 구함",
      "content": "youngburn 서대문구에서 용병 구함",
      "date": "2023-08-01"
    },
    {
      "id": 17,
      "image": "",
      "crewname": "youngburn",
      "postdate": "2023-08-01",
      "exercisedate": "2023-08-10",
      "location": "서울시 서대문구 서대문로 27로 22",
      "nickname": "KimLee",
      "exercisekind": "축구",
      "totalnumber": "2",
      "title": "용병 구함",
      "content": "youngburn 서대문구에서 용병 구함",
      "date": "2023-08-01"
    },
    {
      "id": 18,
      "image": "",
      "crewname": "youngburn",
      "postdate": "2023-08-01",
      "exercisedate": "2023-08-10",
      "location": "서울시 서대문구 서대문로 27로 22",
      "nickname": "KimLee",
      "exercisekind": "축구",
      "totalnumber": "2",
      "title": "용병 구함",
      "content": "youngburn 서대문구에서 용병 구함",
      "date": "2023-08-01"
    },
    {
      "id": 19,
      "image": "",
      "crewname": "youngburn",
      "postdate": "2023-08-01",
      "exercisedate": "2023-08-10",
      "location": "서울시 서대문구 서대문로 27로 22",
      "nickname": "KimLee",
      "exercisekind": "축구",
      "totalnumber": "2",
      "title": "용병 구함",
      "content": "youngburn 서대문구에서 용병 구함",
      "date": "2023-08-01"
    },
    {
      "id": 20,
      "image": "",
      "crewname": "youngburn",
      "postdate": "2023-08-01",
      "exercisedate": "2023-08-10",
      "location": "서울시 서대문구 서대문로 27로 22",
      "nickname": "KimLee",
      "exercisekind": "축구",
      "totalnumber": "2",
      "title": "용병 구함",
      "content": "youngburn 서대문구에서 용병 구함",
      "date": "2023-08-01"
    },
    {
      "id": 21,
      "image": "",
      "crewname": "youngburn",
      "postdate": "2023-08-01",
      "exercisedate": "2023-08-10",
      "location": "서울시 서대문구 서대문로 27로 22",
      "nickname": "KimLee",
      "exercisekind": "축구",
      "totalnumber": "2",
      "title": "용병 구함",
      "content": "youngburn 서대문구에서 용병 구함",
      "date": "2023-08-01"
    }
  ]
}